kinshipsim/__init__.py
kinshipsim/default_pedigree.py
kinshipsim/individual.py
kinshipsim/lib.py
kinshipsim/pedigree.py
kinshipsim/spinner.py
kinshipsim/scripts/__init__.py
kinshipsim/scripts/run_haploidize.py
kinshipsim/scripts/run_init_pedigrees.py
kinshipsim/scripts/run_init_x_chromosome.py
kinshipsim/scripts/run_init_x_pedigrees.py
kinshipsim/scripts/run_maf2vcf.py
kinshipsim/scripts/run_reduce_snps.py
kinshipsim/scripts/run_sim_results.py
kinshipsim/scripts/run_validate_vcf.py
kinshipsim/shell/run_haploidize.sh
kinshipsim/shell/run_ngs.sh
kinshipsim/shell/run_reduce_snps.sh
scripts/__init__.py
scripts/run_validate_vcf.py
kinshipsim-2020.8.dist-info/METADATA
kinshipsim-2020.8.dist-info/WHEEL
kinshipsim-2020.8.dist-info/top_level.txt
kinshipsim-2020.8.dist-info/RECORD
